{
  "version": 1,
  "license": "CC-BY-SA-3.0",
  "copyright": "https://github.com/tgstation/tgstation/commit/68c8d3eb9cc102ec0375be7dda161dd20a0f6bfe",
  "size": {
    "x": 32,
    "y": 32
  },
  "states": [
    {
      "name": "ast_warn_box"
    },
    {
      "name": "ast_warn_corner_ne"
    },
    {
      "name": "ast_warn_corner_nw"
    },
    {
      "name": "ast_warn_corner_se"
    },
    {
      "name": "ast_warn_corner_sw"
    },
    {
      "name": "ast_warn_end_e"
    },
    {
      "name": "ast_warn_end_n"
    },
    {
      "name": "ast_warn_end_s"
    },
    {
      "name": "ast_warn_end_w"
    },
    {
      "name": "ast_warn_full"
    },
    {
      "name": "ast_warn_side_e"
    },
    {
      "name": "ast_warn_side_n"
    },
    {
      "name": "ast_warn_side_ne"
    },
    {
      "name": "ast_warn_side_nw"
    },
    {
      "name": "ast_warn_side_s"
    },
    {
      "name": "ast_warn_side_se"
    },
    {
      "name": "ast_warn_side_sw"
    },
    {
      "name": "ast_warn_side_w"
    }
  ]
}
